haveibeenpywned/__init__.py
haveibeenpywned/haveibeenpywned.py
haveibeenpywned-0.2.93.dist-info/LICENSE.txt
haveibeenpywned-0.2.93.dist-info/METADATA
haveibeenpywned-0.2.93.dist-info/WHEEL
haveibeenpywned-0.2.93.dist-info/top_level.txt
haveibeenpywned-0.2.93.dist-info/RECORD
