Metadata-Version: 2.1
Name: haveibeenpywned
Version: 0.2.93
Summary: A simple python wrapper for the www.haveibeenpwned.com API.
Home-page: https://github.com/scv-m/haveibeenpywned
Author: Sam Neal
Author-email: sam.w.neal@gmail.com
License: UNKNOWN
Platform: UNKNOWN
Classifier: Programming Language :: Python :: 3
Classifier: Operating System :: OS Independent
Requires-Python: >=3.8
Requires-Dist: ratelimit
Requires-Dist: requests
